{
  "entries": [
    {
      "title": "2026-04-01",
      "type": "デイリー",
      "date": "2026-04-01",
      "done": "インバータ更新案件の仕様書初稿レビュー完了、製造課との調整MTG実施（停止時間2時間で合意）、部下Aの週次進捗確認",
      "keep": "MTG前に論点を3点に絞って臨む習慣。製造課との交渉がスムーズになった",
      "problem": "仕様書レビューに予定より1時間超過。細部の確認が増えた",
      "try": "レビュー前日にチェックリストを準備して当日の確認項目を絞る",
      "learning": "インバータのコモンモードノイズ対策はLCフィルタとシールド接地の組み合わせが最も効果的。単独では不十分なケースあり",
      "tomorrow": "仕様書最終版の確認、設備投資稟議資料の骨子作成",
      "task_count": 6
    },
    {
      "title": "2026-04-02",
      "type": "デイリー",
      "date": "2026-04-02",
      "done": "稟議資料骨子完成（投資額500万、ROI2年の試算込み）、防爆エリア計装機器の定期点検スケジュール確認",
      "keep": "稟議資料はエグゼクティブサマリーを最初に書く順番。上司のフィードバックが的確になった",
      "problem": "点検スケジュールの確認で、昨年のデータが一部見当たらなかった",
      "try": "点検記録はフォルダ構成を統一してナレッジベースに保存するルールを作る",
      "learning": "防爆機器（Ex認証）は5年ごとの分解点検が義務。コネクタ部の腐食検査は毎年実施が推奨",
      "tomorrow": "稟議資料の数値根拠確認、部下Bへの仕様検討タスク割り当て",
      "task_count": 5
    },
    {
      "title": "2026-04-03",
      "type": "デイリー",
      "date": "2026-04-03",
      "done": "稟議資料数値根拠確認完了、部下BへのPLC更新仕様検討タスク指示（期限4/10）、他工場との技術情報交換（メール対応3件）",
      "keep": "タスク指示時に「なぜやるか」を先に伝えると部下の理解度が上がる",
      "problem": "他工場への返信メールで丁寧すぎる表現が残っていた。REPORT.mdのルールに照らして修正",
      "try": "社外メールは送信前に禁止表現リストと照合する習慣をつける",
      "learning": "PLCのバックアップは定修前・変更前の2タイミングが鉄則。変更後のバックアップだけでは障害時に戻せない",
      "tomorrow": "月次電力使用量レポート作成、デマンド管理の閾値見直し検討",
      "task_count": 7
    },
    {
      "title": "2026-04-04",
      "type": "デイリー",
      "date": "2026-04-04",
      "done": "月次電力使用量レポート完成（3月は予算比-8%で着地）、デマンドピーク発生要因の分析（空調立ち上がり時刻が原因）",
      "keep": "電力トレンドグラフを見せながら報告すると上司の理解が早い",
      "problem": "分析に使うExcelが重くなっており、データ量が増えると処理に3分以上かかる",
      "try": "電力データの集計をPythonスクリプト化して処理速度を改善する",
      "learning": "デマンドピーク抑制は空調の立ち上がり時刻を15分ずらすだけで5%削減できるケースがある。負荷平準化の効果は大きい",
      "tomorrow": "稟議資料上司提出、電験3種・理論の問題演習（コンデンサ回路）",
      "task_count": 4
    },
    {
      "title": "2026-04-07",
      "type": "デイリー",
      "date": "2026-04-07",
      "done": "稟議資料上司提出完了（フィードバック待ち）、電験理論コンデンサ回路10問演習（正答率80%）、部下C面談（育成計画の中間確認）",
      "keep": "電験の演習は朝の通勤時間に集中してやる習慣が定着してきた",
      "problem": "コンデンサの過渡応答問題でRC時定数の扱いが不正確だった。公式の意味を再確認が必要",
      "try": "フェインマンセッションでRC時定数を自分の言葉で説明し直す",
      "learning": "RC回路の時定数τ=RCは「電圧が初期値の約63%まで変化する時間」。充電・放電で同じ式が使えるが符号と初期条件の設定に注意",
      "tomorrow": "稟議フィードバック対応、PLC更新仕様の中間確認（部下B）",
      "task_count": 5
    },
    {
      "title": "2026-04-08",
      "type": "デイリー",
      "date": "2026-04-08",
      "done": "稟議フィードバック対応（ROIの算出根拠の補強を追加）、部下BのPLC仕様書中間確認（コメント5点フィードバック）、SCATシステム障害対応支援（通信エラー原因調査）",
      "keep": "障害対応時はまず電源品質とアース状態を確認する手順が有効。今日もUPS電圧異常が原因だった",
      "problem": "稟議への追加根拠の収集に予想外に時間がかかった（ベンダーへの確認往復）",
      "try": "仕様検討段階でROI関連のデータを先に集めておく。後から追加する手間を省く",
      "learning": "SCADA通信エラーの原因切り分けは物理層（ケーブル・コネクタ）→ネットワーク層→アプリ層の順に確認するのが効率的",
      "tomorrow": "稟議最終版提出、電験電力科目の変圧器問題演習",
      "task_count": 8
    },
    {
      "title": "2026-04-09",
      "type": "デイリー",
      "date": "2026-04-09",
      "done": "稟議最終版提出完了、変圧器問題15問演習（正答率73%）、チームMTG（週次進捗共有・来週の作業計画確認）",
      "keep": "チームMTGは課題のみ共有し、進捗は事前にドキュメントで確認する形式が時間効率が良い",
      "problem": "変圧器の等価回路（T形回路）の励磁回路の扱いが曖昧。一次換算・二次換算の変換が混乱しやすい",
      "try": "変圧器等価回路の図を書きながら一次換算の手順を整理してknowledgeに保存する",
      "learning": "変圧器の百分率インピーダンス（%Z）は短絡事故電流の計算に直結。%Zが大きいほど短絡電流は小さくなる（保護協調設計に重要）",
      "tomorrow": "設備投資稟議の役員報告準備、知識チェック（電験理論）",
      "task_count": 6
    },
    {
      "title": "2026-04-10",
      "type": "デイリー",
      "date": "2026-04-10",
      "done": "役員報告資料準備完了（10分プレゼン用スライド8枚）、電験理論の知識チェック（RC・RL回路の理解度スコア3→4に更新）、新規採用候補者の技術面接サポート",
      "keep": "役員報告は結論を1枚目に置き、根拠は別スライドに飛ばす構成。質問が的絞りやすくなる",
      "problem": "技術面接のサポート中、評価基準が面接官間で統一されていないことに気づいた",
      "try": "次回採用から電気計装の技術評価チェックリストを作成して面接に持ち込む",
      "learning": "RL回路の過渡応答はRC回路と対称。時定数τ=L/R。エネルギーをコイルが蓄えるため電流変化が遅れる点がRC（電圧変化が遅れる）との違い",
      "tomorrow": "役員報告（14:00）、定修作業計画の最終確認",
      "task_count": 7
    },
    {
      "title": "2026-W14",
      "type": "ウィークリー",
      "date": "2026-04-05",
      "done": "設備投資稟議資料を1週間で初稿から最終提出まで完了。月次電力レポート提出。電験演習25問（理論・電力）",
      "keep": "稟議資料の進め方：骨子→数値根拠→エグゼクティブサマリーの順が効率的。冒頭から完璧を目指さない",
      "problem": "週の後半に集中タスクが重なりやすい。特に木・金に承認系タスクが詰まる傾向",
      "try": "月・火に承認依頼系タスクを前倒しして木・金の負荷を分散させる",
      "learning": "電力デマンド管理と電験3種の知識（デマンド制御・負荷率計算）がリンクした。業務で実感することで公式の意味が深まる",
      "tomorrow": "W15: 役員報告→結果を受けて次フェーズへ。定修作業計画確定。電験電力科目の変圧器・送電線仕上げ",
      "task_count": 22
    },
    {
      "title": "2026-03-31",
      "type": "デイリー",
      "date": "2026-03-31",
      "done": "3月月次レビュー完了（完了タスク31件、持越し4件）、4月の優先案件リスト作成、設備計画書の整理・アーカイブ",
      "keep": "月末に翌月の優先3案件を決めておくと4月の初動が速かった",
      "problem": "持越しタスクが4件あり、うち2件は期限切れになっていた。優先度管理の見直しが必要",
      "try": "毎週金曜に持越しタスクの棚卸しをして期限切れを防ぐ",
      "learning": "過去の稟議資料をアーカイブしながら気づいた：投資根拠の書き方が年度ごとにバラバラ。テンプレート化の必要性を再確認",
      "tomorrow": "4月の業務スタート：インバータ更新案件の仕様書レビューから着手",
      "task_count": 5
    }
  ],
  "exported_at": "2026-04-10T18:00:00"
}
